eco-transformer/__init__.py
eco-transformer/main.py
eco_transformer/__init__.py
eco_transformer/main.py
eco_transformer-0.1.6.dist-info/licenses/LICENCE
eco_transformer-0.1.6.dist-info/METADATA
eco_transformer-0.1.6.dist-info/WHEEL
eco_transformer-0.1.6.dist-info/entry_points.txt
eco_transformer-0.1.6.dist-info/top_level.txt
eco_transformer-0.1.6.dist-info/RECORD
