Metadata-Version: 2.4
Name: eco_transformer
Version: 0.1.6
Summary: Optimize LLM outputs and track emissions
Home-page: https://github.com/viji123450/eco_transformer
Author: Vijayalakshmi
Author-email: viji814881@email.com
License: MIT
Requires-Python: >=3.8
License-File: LICENCE
Requires-Dist: torch>=1.13.0
Requires-Dist: transformers>=4.30.0
Requires-Dist: codecarbon>=2.2.2
Requires-Dist: evaluate>=0.4.0
Requires-Dist: numpy>=1.24.0
Requires-Dist: rouge_score>=0.1.2
Requires-Dist: nltk>=3.8.0
Requires-Dist: absl-py>=1.4.0
Dynamic: author
Dynamic: author-email
Dynamic: description-content-type
Dynamic: home-page
Dynamic: license
Dynamic: license-file
Dynamic: requires-dist
Dynamic: requires-python
Dynamic: summary
